sparselsh/__init__.py
sparselsh/cli.py
sparselsh/lsh.py
sparselsh/storage.py
tests/__init__.py
tests/base_test.py
tests/extra_data_tests.py
tests/regression_tests.py
tests/test_benchmark.py
tests/test_bruteforce_e2e.py
tests/test_input_matrix.py
tests/test_no_extra_data.py
sparselsh-2.2.0.dist-info/LICENSE
sparselsh-2.2.0.dist-info/METADATA
sparselsh-2.2.0.dist-info/WHEEL
sparselsh-2.2.0.dist-info/entry_points.txt
sparselsh-2.2.0.dist-info/top_level.txt
sparselsh-2.2.0.dist-info/RECORD
