Metadata-Version: 2.1
Name: sparselsh
Version: 2.2.0
Summary: A locality sensitive hashing library with an emphasis on large, sparse datasets.
Home-page: https://github.com/brandonrobertz/sparselsh
Download-URL: https://github.com/brandonrobertz/SparseLSH
Author: Brandon Roberts
Author-email: brandon@bxroberts.org
Keywords: clustering,sparse,lsh
Classifier: Intended Audience :: Developers
Classifier: License :: OSI Approved :: MIT License
Classifier: Operating System :: OS Independent
Classifier: Programming Language :: Python
Classifier: Programming Language :: Python :: 3
Classifier: Topic :: Software Development :: Libraries
License-File: LICENSE
Requires-Dist: numpy <2.0,>=1.18.6
Requires-Dist: scipy <2.0,>=1.0.0
Requires-Dist: scikit-learn <2.0,>=0.24.0
Provides-Extra: leveldb
Requires-Dist: leveldb <1.0,>=0.201 ; extra == 'leveldb'
Provides-Extra: lint
Requires-Dist: flake8 ; extra == 'lint'
Provides-Extra: redis
Requires-Dist: redis <3.0,>=2.10.1 ; extra == 'redis'
Provides-Extra: test
Requires-Dist: pytest ; extra == 'test'
